ApachecnSecZhPt2/404.html
ApachecnSecZhPt2/CNAME
ApachecnSecZhPt2/Dockerfile
ApachecnSecZhPt2/LICENSE
ApachecnSecZhPt2/LICENSE_ETC
ApachecnSecZhPt2/NAV.md
ApachecnSecZhPt2/README.md
ApachecnSecZhPt2/SUMMARY.md
ApachecnSecZhPt2/__init__.py
ApachecnSecZhPt2/__main__.py
ApachecnSecZhPt2/index.html
ApachecnSecZhPt2/update.sh
ApachecnSecZhPt2/asset/LXGWWenKaiScreen.ttf
ApachecnSecZhPt2/asset/__init__.py
ApachecnSecZhPt2/asset/back-to-top.css
ApachecnSecZhPt2/asset/back-to-top.js
ApachecnSecZhPt2/asset/dark-mode.css
ApachecnSecZhPt2/asset/dark-mode.js
ApachecnSecZhPt2/asset/docsify-apachecn-footer.js
ApachecnSecZhPt2/asset/docsify-baidu-push.js
ApachecnSecZhPt2/asset/docsify-baidu-stat.js
ApachecnSecZhPt2/asset/docsify-clicker.js
ApachecnSecZhPt2/asset/docsify-cnzz.js
ApachecnSecZhPt2/asset/docsify-copy-code.min.js
ApachecnSecZhPt2/asset/docsify-katex.js
ApachecnSecZhPt2/asset/docsify-quick-page.css
ApachecnSecZhPt2/asset/docsify-quick-page.js
ApachecnSecZhPt2/asset/docsify-sidebar-collapse.min.js
ApachecnSecZhPt2/asset/docsify.min.js
ApachecnSecZhPt2/asset/edit.css
ApachecnSecZhPt2/asset/edit.js
ApachecnSecZhPt2/asset/edit.svg
ApachecnSecZhPt2/asset/katex.min.css
ApachecnSecZhPt2/asset/left.svg
ApachecnSecZhPt2/asset/lxgw-wenkai.css
ApachecnSecZhPt2/asset/moon.svg
ApachecnSecZhPt2/asset/prism-c.min.js
ApachecnSecZhPt2/asset/prism-cpp.min.js
ApachecnSecZhPt2/asset/prism-csharp.min.js
ApachecnSecZhPt2/asset/prism-darcula.css
ApachecnSecZhPt2/asset/prism-java.min.js
ApachecnSecZhPt2/asset/prism-javascript.min.js
ApachecnSecZhPt2/asset/prism-php.min.js
ApachecnSecZhPt2/asset/prism-python.min.js
ApachecnSecZhPt2/asset/right.svg
ApachecnSecZhPt2/asset/search.min.js
ApachecnSecZhPt2/asset/share.css
ApachecnSecZhPt2/asset/share.js
ApachecnSecZhPt2/asset/share.svg
ApachecnSecZhPt2/asset/sidebar.min.css
ApachecnSecZhPt2/asset/style.css
ApachecnSecZhPt2/asset/sun.svg
ApachecnSecZhPt2/asset/up.svg
ApachecnSecZhPt2/asset/vue.css
ApachecnSecZhPt2/asset/fonts/KaTeX_AMS-Regular.ttf
apachecn_sec_zh_pt2-2022.3.20.0.dist-info/METADATA
apachecn_sec_zh_pt2-2022.3.20.0.dist-info/WHEEL
apachecn_sec_zh_pt2-2022.3.20.0.dist-info/entry_points.txt
apachecn_sec_zh_pt2-2022.3.20.0.dist-info/top_level.txt
apachecn_sec_zh_pt2-2022.3.20.0.dist-info/RECORD
